videosplatter/__init__.py
videosplatter/splat.py
videosplatter-0.3.dist-info/LICENSE
videosplatter-0.3.dist-info/METADATA
videosplatter-0.3.dist-info/WHEEL
videosplatter-0.3.dist-info/entry_points.txt
videosplatter-0.3.dist-info/top_level.txt
videosplatter-0.3.dist-info/RECORD
