Metadata-Version: 2.1
Name: videosplatter
Version: 0.3
Summary: Splat videos
Home-page: https://github.com/ryanfox/videosplatter
Author: Ryan Fox
Author-email: ryan@foxrow.com
License: ACSL
Platform: UNKNOWN
Requires-Python: >=3.6
License-File: LICENSE
Requires-Dist: moviepy (==1.0.3)
Requires-Dist: opencv-python (==4.5.5.62)
